{"mepsLanguageSpoken": "LSB", "mepsLanguageWritten": "LSB", "bibleBookChapter": 17, "bibleBookNumber": 19, "type": "bible", "markers": [{"duration": "00:00:09.350", "verseNumber": 0, "startTime": "00:00:01.502", "label": "Salmo 17:0", "endTransitionDuration": "00:00:00.000"}, {"duration": "00:00:18.968", "verseNumber": 1, "startTime": "00:00:10.853", "label": "Salmo 17:1", "endTransitionDuration": "00:00:00.000"}, {"duration": "00:00:07.647", "verseNumber": 2, "startTime": "00:00:29.821", "label": "Salmo 17:2", "endTransitionDuration": "00:00:00.000"}, {"duration": "00:00:27.083", "verseNumber": 3, "startTime": "00:00:37.468", "label": "Salmo 17:3", "endTransitionDuration": "00:00:00.000"}, {"duration": "00:00:06.612", "verseNumber": 4, "startTime": "00:01:04.551", "label": "Salmo 17:4", "endTransitionDuration": "00:00:00.000"}, {"duration": "00:00:12.155", "verseNumber": 5, "startTime": "00:01:11.164", "label": "Salmo 17:5", "endTransitionDuration": "00:00:00.000"}, {"duration": "00:00:12.055", "verseNumber": 6, "startTime": "00:01:23.319", "label": "Salmo 17:6", "endTransitionDuration": "00:00:00.000"}, {"duration": "00:00:29.353", "verseNumber": 7, "startTime": "00:01:35.375", "label": "Salmo 17:7", "endTransitionDuration": "00:00:01.001"}, {"duration": "00:00:20.971", "verseNumber": 8, "startTime": "00:02:04.729", "label": "Salmo 17:8", "endTransitionDuration": "00:00:00.000"}, {"duration": "00:00:08.315", "verseNumber": 9, "startTime": "00:02:25.701", "label": "Salmo 17:9", "endTransitionDuration": "00:00:00.000"}, {"duration": "00:00:05.743", "verseNumber": 10, "startTime": "00:02:34.016", "label": "Salmo 17:10", "endTransitionDuration": "00:00:00.000"}, {"duration": "00:00:07.680", "verseNumber": 11, "startTime": "00:02:39.760", "label": "Salmo 17:11", "endTransitionDuration": "00:00:00.000"}, {"duration": "00:00:10.920", "verseNumber": 12, "startTime": "00:02:47.441", "label": "Salmo 17:12", "endTransitionDuration": "00:00:00.000"}, {"duration": "00:00:10.385", "verseNumber": 13, "startTime": "00:02:58.361", "label": "Salmo 17:13", "endTransitionDuration": "00:00:00.000"}, {"duration": "00:00:23.576", "verseNumber": 14, "startTime": "00:03:08.746", "label": "Salmo 17:14", "endTransitionDuration": "00:00:00.000"}, {"duration": "00:00:25.446", "verseNumber": 15, "startTime": "00:03:32.323", "label": "Salmo 17:15", "endTransitionDuration": "00:00:06.678"}], "hash": "12345678901234567890123456789012", "introduction": {"duration": "00:00:01.502", "startTime": "00:00:00.000"}, "BookName": "Salmos", "file": "https://download-a.akamaihd.net/files/media_publication/bc/nwt_19_Ps_LSB_017_r720P.mp4"}