{"mepsLanguageSpoken": "LSB", "mepsLanguageWritten": "LSB", "bibleBookChapter": 22, "bibleBookNumber": 19, "type": "bible", "markers": [{"duration": "00:00:19.753", "verseNumber": 0, "startTime": "00:00:01.501", "label": "Salmo 22:0", "endTransitionDuration": "00:00:01.000"}, {"duration": "00:00:17.550", "verseNumber": 1, "startTime": "00:00:21.254", "label": "Salmo 22:1", "endTransitionDuration": "00:00:00.000"}, {"duration": "00:00:14.814", "verseNumber": 2, "startTime": "00:00:38.805", "label": "Salmo 22:2", "endTransitionDuration": "00:00:00.000"}, {"duration": "00:00:09.209", "verseNumber": 3, "startTime": "00:00:53.620", "label": "Salmo 22:3", "endTransitionDuration": "00:00:00.000"}, {"duration": "00:00:09.709", "verseNumber": 4, "startTime": "00:01:02.829", "label": "Salmo 22:4", "endTransitionDuration": "00:00:00.000"}, {"duration": "00:00:12.078", "verseNumber": 5, "startTime": "00:01:12.539", "label": "Salmo 22:5", "endTransitionDuration": "00:00:00.000"}, {"duration": "00:00:19.719", "verseNumber": 6, "startTime": "00:01:24.617", "label": "Salmo 22:6", "endTransitionDuration": "00:00:00.000"}, {"duration": "00:00:08.074", "verseNumber": 7, "startTime": "00:01:44.337", "label": "Salmo 22:7", "endTransitionDuration": "00:00:00.000"}, {"duration": "00:00:21.621", "verseNumber": 8, "startTime": "00:01:52.412", "label": "Salmo 22:8", "endTransitionDuration": "00:00:01.000"}, {"duration": "00:00:19.085", "verseNumber": 9, "startTime": "00:02:14.033", "label": "Salmo 22:9", "endTransitionDuration": "00:00:00.000"}, {"duration": "00:00:21.721", "verseNumber": 10, "startTime": "00:02:33.119", "label": "Salmo 22:10", "endTransitionDuration": "00:00:00.000"}, {"duration": "00:00:15.548", "verseNumber": 11, "startTime": "00:02:54.841", "label": "Salmo 22:11", "endTransitionDuration": "00:00:00.000"}, {"duration": "00:00:14.681", "verseNumber": 12, "startTime": "00:03:10.390", "label": "Salmo 22:12", "endTransitionDuration": "00:00:00.000"}, {"duration": "00:00:15.048", "verseNumber": 13, "startTime": "00:03:25.071", "label": "Salmo 22:13", "endTransitionDuration": "00:00:00.000"}, {"duration": "00:00:35.135", "verseNumber": 14, "startTime": "00:03:40.119", "label": "Salmo 22:14", "endTransitionDuration": "00:00:00.000"}, {"duration": "00:00:30.196", "verseNumber": 15, "startTime": "00:04:15.255", "label": "Salmo 22:15", "endTransitionDuration": "00:00:01.000"}, {"duration": "00:00:16.116", "verseNumber": 16, "startTime": "00:04:45.451", "label": "Salmo 22:16", "endTransitionDuration": "00:00:00.000"}, {"duration": "00:00:14.647", "verseNumber": 17, "startTime": "00:05:01.567", "label": "Salmo 22:17", "endTransitionDuration": "00:00:00.000"}, {"duration": "00:00:18.284", "verseNumber": 18, "startTime": "00:05:16.215", "label": "Salmo 22:18", "endTransitionDuration": "00:00:00.000"}, {"duration": "00:00:11.711", "verseNumber": 19, "startTime": "00:05:34.500", "label": "Salmo 22:19", "endTransitionDuration": "00:00:00.000"}, {"duration": "00:00:11.878", "verseNumber": 20, "startTime": "00:05:46.212", "label": "Salmo 22:20", "endTransitionDuration": "00:00:00.000"}, {"duration": "00:00:21.521", "verseNumber": 21, "startTime": "00:05:58.091", "label": "Salmo 22:21", "endTransitionDuration": "00:00:00.000"}, {"duration": "00:00:18.752", "verseNumber": 22, "startTime": "00:06:19.612", "label": "Salmo 22:22", "endTransitionDuration": "00:00:01.000"}, {"duration": "00:00:13.713", "verseNumber": 23, "startTime": "00:06:38.364", "label": "Salmo 22:23", "endTransitionDuration": "00:00:00.000"}, {"duration": "00:00:14.147", "verseNumber": 24, "startTime": "00:06:52.078", "label": "Salmo 22:24", "endTransitionDuration": "00:00:00.000"}, {"duration": "00:00:19.853", "verseNumber": 25, "startTime": "00:07:06.225", "label": "Salmo 22:25", "endTransitionDuration": "00:00:00.000"}, {"duration": "00:00:14.381", "verseNumber": 26, "startTime": "00:07:26.078", "label": "Salmo 22:26", "endTransitionDuration": "00:00:00.000"}, {"duration": "00:00:14.981", "verseNumber": 27, "startTime": "00:07:40.460", "label": "Salmo 22:27", "endTransitionDuration": "00:00:00.000"}, {"duration": "00:00:06.639", "verseNumber": 28, "startTime": "00:07:55.441", "label": "Salmo 22:28", "endTransitionDuration": "00:00:00.000"}, {"duration": "00:00:24.090", "verseNumber": 29, "startTime": "00:08:02.081", "label": "Salmo 22:29", "endTransitionDuration": "00:00:00.000"}, {"duration": "00:00:11.811", "verseNumber": 30, "startTime": "00:08:26.172", "label": "Salmo 22:30", "endTransitionDuration": "00:00:00.000"}, {"duration": "00:00:31.031", "verseNumber": 31, "startTime": "00:08:37.984", "label": "Salmo 22:31", "endTransitionDuration": "00:00:06.673"}], "hash": "12345678901234567890123456789012", "introduction": {"duration": "00:00:01.501", "startTime": "00:00:00.000"}, "BookName": "Salmos", "file": "https://download-a.akamaihd.net/files/media_publication/56/nwt_19_Ps_LSB_022_r720P.mp4"}