{"mepsLanguageSpoken": "LSB", "mepsLanguageWritten": "LSB", "bibleBookChapter": 13, "bibleBookNumber": 28, "type": "bible", "markers": [{"duration": "00:00:36.903", "verseNumber": 1, "startTime": "00:00:02.001", "label": "Oseias 13:1", "endTransitionDuration": "00:00:00.000"}, {"duration": "00:00:28.628", "verseNumber": 2, "startTime": "00:00:38.905", "label": "Oseias 13:2", "endTransitionDuration": "00:00:00.000"}, {"duration": "00:00:47.781", "verseNumber": 3, "startTime": "00:01:07.534", "label": "Oseias 13:3", "endTransitionDuration": "00:00:01.167"}, {"duration": "00:00:18.585", "verseNumber": 4, "startTime": "00:01:55.315", "label": "Oseias 13:4", "endTransitionDuration": "00:00:00.000"}, {"duration": "00:00:10.110", "verseNumber": 5, "startTime": "00:02:13.900", "label": "Oseias 13:5", "endTransitionDuration": "00:00:00.000"}, {"duration": "00:00:21.121", "verseNumber": 6, "startTime": "00:02:24.010", "label": "Oseias 13:6", "endTransitionDuration": "00:00:01.167"}, {"duration": "00:00:21.187", "verseNumber": 7, "startTime": "00:02:45.131", "label": "Oseias 13:7", "endTransitionDuration": "00:00:00.000"}, {"duration": "00:00:39.739", "verseNumber": 8, "startTime": "00:03:06.319", "label": "Oseias 13:8", "endTransitionDuration": "00:00:00.000"}, {"duration": "00:00:17.650", "verseNumber": 9, "startTime": "00:03:46.059", "label": "Oseias 13:9", "endTransitionDuration": "00:00:01.167"}, {"duration": "00:00:27.927", "verseNumber": 10, "startTime": "00:04:03.710", "label": "Oseias 13:10", "endTransitionDuration": "00:00:00.000"}, {"duration": "00:00:11.444", "verseNumber": 11, "startTime": "00:04:31.638", "label": "Oseias 13:11", "endTransitionDuration": "00:00:00.000"}, {"duration": "00:00:17.083", "verseNumber": 12, "startTime": "00:04:43.082", "label": "Oseias 13:12", "endTransitionDuration": "00:00:00.000"}, {"duration": "00:00:30.063", "verseNumber": 13, "startTime": "00:05:00.166", "label": "Oseias 13:13", "endTransitionDuration": "00:00:01.167"}, {"duration": "00:00:58.491", "verseNumber": 14, "startTime": "00:05:30.229", "label": "Oseias 13:14", "endTransitionDuration": "00:00:00.000"}, {"duration": "00:00:49.249", "verseNumber": 15, "startTime": "00:06:28.721", "label": "Oseias 13:15", "endTransitionDuration": "00:00:00.000"}, {"duration": "00:00:42.475", "verseNumber": 16, "startTime": "00:07:17.970", "label": "Oseias 13:16", "endTransitionDuration": "00:00:01.000"}], "hash": "12345678901234567890123456789012", "introduction": {"duration": "00:00:02.001", "startTime": "00:00:00.000"}, "BookName": "Oseias", "file": "https://download-a.akamaihd.net/files/media_publication/39/nwt_28_Ho_LSB_13_r720P.mp4"}