{"mepsLanguageSpoken": "LSB", "mepsLanguageWritten": "LSB", "bibleBookChapter": 12, "bibleBookNumber": 1, "type": "bible", "markers": [{"duration": "00:00:16.483", "verseNumber": 1, "startTime": "00:00:02.001", "label": "G\u00eanesis 12:1", "endTransitionDuration": "00:00:00.000"}, {"duration": "00:00:18.618", "verseNumber": 2, "startTime": "00:00:18.485", "label": "G\u00eanesis 12:2", "endTransitionDuration": "00:00:00.000"}, {"duration": "00:00:19.719", "verseNumber": 3, "startTime": "00:00:37.103", "label": "G\u00eanesis 12:3", "endTransitionDuration": "00:00:01.000"}, {"duration": "00:00:15.682", "verseNumber": 4, "startTime": "00:00:56.823", "label": "G\u00eanesis 12:4", "endTransitionDuration": "00:00:00.000"}, {"duration": "00:00:17.717", "verseNumber": 5, "startTime": "00:01:12.505", "label": "G\u00eanesis 12:5", "endTransitionDuration": "00:00:00.000"}, {"duration": "00:00:22.989", "verseNumber": 6, "startTime": "00:01:30.223", "label": "G\u00eanesis 12:6", "endTransitionDuration": "00:00:00.000"}, {"duration": "00:00:24.657", "verseNumber": 7, "startTime": "00:01:53.213", "label": "G\u00eanesis 12:7", "endTransitionDuration": "00:00:00.000"}, {"duration": "00:00:34.467", "verseNumber": 8, "startTime": "00:02:17.871", "label": "G\u00eanesis 12:8", "endTransitionDuration": "00:00:00.000"}, {"duration": "00:00:15.148", "verseNumber": 9, "startTime": "00:02:52.338", "label": "G\u00eanesis 12:9", "endTransitionDuration": "00:00:01.000"}, {"duration": "00:00:20.153", "verseNumber": 10, "startTime": "00:03:07.487", "label": "G\u00eanesis 12:10", "endTransitionDuration": "00:00:00.000"}, {"duration": "00:00:06.473", "verseNumber": 11, "startTime": "00:03:27.640", "label": "G\u00eanesis 12:11", "endTransitionDuration": "00:00:00.000"}, {"duration": "00:00:08.575", "verseNumber": 12, "startTime": "00:03:34.113", "label": "G\u00eanesis 12:12", "endTransitionDuration": "00:00:00.000"}, {"duration": "00:00:06.506", "verseNumber": 13, "startTime": "00:03:42.689", "label": "G\u00eanesis 12:13", "endTransitionDuration": "00:00:00.000"}, {"duration": "00:00:07.474", "verseNumber": 14, "startTime": "00:03:49.195", "label": "G\u00eanesis 12:14", "endTransitionDuration": "00:00:00.000"}, {"duration": "00:00:19.552", "verseNumber": 15, "startTime": "00:03:56.669", "label": "G\u00eanesis 12:15", "endTransitionDuration": "00:00:00.000"}, {"duration": "00:00:17.817", "verseNumber": 16, "startTime": "00:04:16.222", "label": "G\u00eanesis 12:16", "endTransitionDuration": "00:00:00.000"}, {"duration": "00:00:14.047", "verseNumber": 17, "startTime": "00:04:34.040", "label": "G\u00eanesis 12:17", "endTransitionDuration": "00:00:00.000"}, {"duration": "00:00:08.274", "verseNumber": 18, "startTime": "00:04:48.087", "label": "G\u00eanesis 12:18", "endTransitionDuration": "00:00:00.000"}, {"duration": "00:00:11.578", "verseNumber": 19, "startTime": "00:04:56.362", "label": "G\u00eanesis 12:19", "endTransitionDuration": "00:00:00.000"}, {"duration": "00:00:26.292", "verseNumber": 20, "startTime": "00:05:07.940", "label": "G\u00eanesis 12:20", "endTransitionDuration": "00:00:06.673"}], "hash": "12345678901234567890123456789012", "introduction": {"duration": "00:00:02.001", "startTime": "00:00:00.000"}, "BookName": "G\u00eanesis", "file": "https://download-a.akamaihd.net/files/media_publication/a5/nwt_01_Ge_LSB_12_r720P.mp4"}