{"mepsLanguageSpoken": "LSB", "mepsLanguageWritten": "LSB", "bibleBookChapter": 8, "bibleBookNumber": 20, "type": "bible", "markers": [{"duration": "00:00:11.578", "verseNumber": 1, "startTime": "00:00:01.501", "label": "Prov\u00e9rbios 8:1", "endTransitionDuration": "00:00:00.000"}, {"duration": "00:00:14.814", "verseNumber": 2, "startTime": "00:00:13.079", "label": "Prov\u00e9rbios 8:2", "endTransitionDuration": "00:00:00.000"}, {"duration": "00:00:11.277", "verseNumber": 3, "startTime": "00:00:27.894", "label": "Prov\u00e9rbios 8:3", "endTransitionDuration": "00:00:00.000"}, {"duration": "00:00:09.242", "verseNumber": 4, "startTime": "00:00:39.172", "label": "Prov\u00e9rbios 8:4", "endTransitionDuration": "00:00:00.000"}, {"duration": "00:00:14.981", "verseNumber": 5, "startTime": "00:00:48.415", "label": "Prov\u00e9rbios 8:5", "endTransitionDuration": "00:00:00.000"}, {"duration": "00:00:08.575", "verseNumber": 6, "startTime": "00:01:03.396", "label": "Prov\u00e9rbios 8:6", "endTransitionDuration": "00:00:00.000"}, {"duration": "00:00:09.042", "verseNumber": 7, "startTime": "00:01:11.971", "label": "Prov\u00e9rbios 8:7", "endTransitionDuration": "00:00:00.000"}, {"duration": "00:00:08.842", "verseNumber": 8, "startTime": "00:01:21.014", "label": "Prov\u00e9rbios 8:8", "endTransitionDuration": "00:00:00.000"}, {"duration": "00:00:16.116", "verseNumber": 9, "startTime": "00:01:29.856", "label": "Prov\u00e9rbios 8:9", "endTransitionDuration": "00:00:00.000"}, {"duration": "00:00:17.083", "verseNumber": 10, "startTime": "00:01:45.972", "label": "Prov\u00e9rbios 8:10", "endTransitionDuration": "00:00:00.000"}, {"duration": "00:00:20.987", "verseNumber": 11, "startTime": "00:02:03.056", "label": "Prov\u00e9rbios 8:11", "endTransitionDuration": "00:00:01.000"}, {"duration": "00:00:19.953", "verseNumber": 12, "startTime": "00:02:24.043", "label": "Prov\u00e9rbios 8:12", "endTransitionDuration": "00:00:00.000"}, {"duration": "00:00:22.122", "verseNumber": 13, "startTime": "00:02:43.997", "label": "Prov\u00e9rbios 8:13", "endTransitionDuration": "00:00:00.000"}, {"duration": "00:00:11.378", "verseNumber": 14, "startTime": "00:03:06.119", "label": "Prov\u00e9rbios 8:14", "endTransitionDuration": "00:00:00.000"}, {"duration": "00:00:18.518", "verseNumber": 15, "startTime": "00:03:17.497", "label": "Prov\u00e9rbios 8:15", "endTransitionDuration": "00:00:00.000"}, {"duration": "00:00:17.417", "verseNumber": 16, "startTime": "00:03:36.015", "label": "Prov\u00e9rbios 8:16", "endTransitionDuration": "00:00:01.000"}, {"duration": "00:00:14.514", "verseNumber": 17, "startTime": "00:03:53.433", "label": "Prov\u00e9rbios 8:17", "endTransitionDuration": "00:00:00.000"}, {"duration": "00:00:15.148", "verseNumber": 18, "startTime": "00:04:07.947", "label": "Prov\u00e9rbios 8:18", "endTransitionDuration": "00:00:00.000"}, {"duration": "00:00:17.117", "verseNumber": 19, "startTime": "00:04:23.096", "label": "Prov\u00e9rbios 8:19", "endTransitionDuration": "00:00:00.000"}, {"duration": "00:00:15.949", "verseNumber": 20, "startTime": "00:04:40.213", "label": "Prov\u00e9rbios 8:20", "endTransitionDuration": "00:00:00.000"}, {"duration": "00:00:15.815", "verseNumber": 21, "startTime": "00:04:56.162", "label": "Prov\u00e9rbios 8:21", "endTransitionDuration": "00:00:01.000"}, {"duration": "00:00:13.780", "verseNumber": 22, "startTime": "00:05:11.978", "label": "Prov\u00e9rbios 8:22", "endTransitionDuration": "00:00:00.000"}, {"duration": "00:00:06.172", "verseNumber": 23, "startTime": "00:05:25.758", "label": "Prov\u00e9rbios 8:23", "endTransitionDuration": "00:00:00.000"}, {"duration": "00:00:12.579", "verseNumber": 24, "startTime": "00:05:31.931", "label": "Prov\u00e9rbios 8:24", "endTransitionDuration": "00:00:00.000"}, {"duration": "00:00:11.811", "verseNumber": 25, "startTime": "00:05:44.510", "label": "Prov\u00e9rbios 8:25", "endTransitionDuration": "00:00:00.000"}, {"duration": "00:00:10.110", "verseNumber": 26, "startTime": "00:05:56.322", "label": "Prov\u00e9rbios 8:26", "endTransitionDuration": "00:00:00.000"}, {"duration": "00:00:26.226", "verseNumber": 27, "startTime": "00:06:06.432", "label": "Prov\u00e9rbios 8:27", "endTransitionDuration": "00:00:00.000"}, {"duration": "00:00:17.183", "verseNumber": 28, "startTime": "00:06:32.658", "label": "Prov\u00e9rbios 8:28", "endTransitionDuration": "00:00:00.000"}, {"duration": "00:00:30.964", "verseNumber": 29, "startTime": "00:06:49.842", "label": "Prov\u00e9rbios 8:29", "endTransitionDuration": "00:00:00.000"}, {"duration": "00:00:19.352", "verseNumber": 30, "startTime": "00:07:20.807", "label": "Prov\u00e9rbios 8:30", "endTransitionDuration": "00:00:00.000"}, {"duration": "00:00:24.424", "verseNumber": 31, "startTime": "00:07:40.159", "label": "Prov\u00e9rbios 8:31", "endTransitionDuration": "00:00:01.000"}, {"duration": "00:00:15.615", "verseNumber": 32, "startTime": "00:08:04.584", "label": "Prov\u00e9rbios 8:32", "endTransitionDuration": "00:00:00.000"}, {"duration": "00:00:08.007", "verseNumber": 33, "startTime": "00:08:20.199", "label": "Prov\u00e9rbios 8:33", "endTransitionDuration": "00:00:00.000"}, {"duration": "00:00:21.955", "verseNumber": 34, "startTime": "00:08:28.207", "label": "Prov\u00e9rbios 8:34", "endTransitionDuration": "00:00:00.000"}, {"duration": "00:00:10.777", "verseNumber": 35, "startTime": "00:08:50.162", "label": "Prov\u00e9rbios 8:35", "endTransitionDuration": "00:00:00.000"}, {"duration": "00:00:18.985", "verseNumber": 36, "startTime": "00:09:00.940", "label": "Prov\u00e9rbios 8:36", "endTransitionDuration": "00:00:05.005"}], "hash": "12345678901234567890123456789012", "introduction": {"duration": "00:00:01.501", "startTime": "00:00:00.000"}, "BookName": "Prov\u00e9rbios", "file": "https://download-a.akamaihd.net/files/media_publication/7a/nwt_20_Pr_LSB_08_r720P.mp4"}