{"mepsLanguageSpoken": "LSB", "mepsLanguageWritten": "LSB", "bibleBookChapter": 16, "bibleBookNumber": 4, "type": "bible", "markers": [{"duration": "00:00:32.532", "verseNumber": 1, "startTime": "00:00:02.001", "label": "N\u00fameros 16:1", "endTransitionDuration": "00:00:00.000"}, {"duration": "00:00:19.352", "verseNumber": 2, "startTime": "00:00:34.534", "label": "N\u00fameros 16:2", "endTransitionDuration": "00:00:00.000"}, {"duration": "00:00:19.886", "verseNumber": 3, "startTime": "00:00:53.887", "label": "N\u00fameros 16:3", "endTransitionDuration": "00:00:00.000"}, {"duration": "00:00:04.871", "verseNumber": 4, "startTime": "00:01:13.773", "label": "N\u00fameros 16:4", "endTransitionDuration": "00:00:00.000"}, {"duration": "00:00:22.489", "verseNumber": 5, "startTime": "00:01:18.645", "label": "N\u00fameros 16:5", "endTransitionDuration": "00:00:00.000"}, {"duration": "00:00:10.744", "verseNumber": 6, "startTime": "00:01:41.134", "label": "N\u00fameros 16:6", "endTransitionDuration": "00:00:00.000"}, {"duration": "00:00:39.506", "verseNumber": 7, "startTime": "00:01:51.878", "label": "N\u00fameros 16:7", "endTransitionDuration": "00:00:01.167"}, {"duration": "00:00:15.081", "verseNumber": 8, "startTime": "00:02:31.384", "label": "N\u00fameros 16:8", "endTransitionDuration": "00:00:00.000"}, {"duration": "00:00:24.991", "verseNumber": 9, "startTime": "00:02:46.466", "label": "N\u00fameros 16:9", "endTransitionDuration": "00:00:00.000"}, {"duration": "00:00:18.685", "verseNumber": 10, "startTime": "00:03:11.457", "label": "N\u00fameros 16:10", "endTransitionDuration": "00:00:00.000"}, {"duration": "00:00:14.047", "verseNumber": 11, "startTime": "00:03:30.143", "label": "N\u00fameros 16:11", "endTransitionDuration": "00:00:01.167"}, {"duration": "00:00:26.026", "verseNumber": 12, "startTime": "00:03:44.190", "label": "N\u00fameros 16:12", "endTransitionDuration": "00:00:00.000"}, {"duration": "00:00:30.864", "verseNumber": 13, "startTime": "00:04:10.216", "label": "N\u00fameros 16:13", "endTransitionDuration": "00:00:00.000"}, {"duration": "00:00:34.100", "verseNumber": 14, "startTime": "00:04:41.080", "label": "N\u00fameros 16:14", "endTransitionDuration": "00:00:00.000"}, {"duration": "00:00:38.338", "verseNumber": 15, "startTime": "00:05:15.181", "label": "N\u00fameros 16:15", "endTransitionDuration": "00:00:01.167"}, {"duration": "00:00:20.220", "verseNumber": 16, "startTime": "00:05:53.519", "label": "N\u00fameros 16:16", "endTransitionDuration": "00:00:00.000"}, {"duration": "00:00:17.183", "verseNumber": 17, "startTime": "00:06:13.740", "label": "N\u00fameros 16:17", "endTransitionDuration": "00:00:00.000"}, {"duration": "00:00:29.229", "verseNumber": 18, "startTime": "00:06:30.923", "label": "N\u00fameros 16:18", "endTransitionDuration": "00:00:00.000"}, {"duration": "00:00:16.316", "verseNumber": 19, "startTime": "00:07:00.153", "label": "N\u00fameros 16:19", "endTransitionDuration": "00:00:00.000"}, {"duration": "00:00:04.137", "verseNumber": 20, "startTime": "00:07:16.469", "label": "N\u00fameros 16:20", "endTransitionDuration": "00:00:00.000"}, {"duration": "00:00:08.975", "verseNumber": 21, "startTime": "00:07:20.606", "label": "N\u00fameros 16:21", "endTransitionDuration": "00:00:00.000"}, {"duration": "00:00:23.923", "verseNumber": 22, "startTime": "00:07:29.582", "label": "N\u00fameros 16:22", "endTransitionDuration": "00:00:01.167"}, {"duration": "00:00:02.736", "verseNumber": 23, "startTime": "00:07:53.506", "label": "N\u00fameros 16:23", "endTransitionDuration": "00:00:00.000"}, {"duration": "00:00:24.457", "verseNumber": 24, "startTime": "00:07:56.242", "label": "N\u00fameros 16:24", "endTransitionDuration": "00:00:00.000"}, {"duration": "00:00:16.716", "verseNumber": 25, "startTime": "00:08:20.700", "label": "N\u00fameros 16:25", "endTransitionDuration": "00:00:00.000"}, {"duration": "00:00:28.261", "verseNumber": 26, "startTime": "00:08:37.416", "label": "N\u00fameros 16:26", "endTransitionDuration": "00:00:00.000"}, {"duration": "00:00:23.823", "verseNumber": 27, "startTime": "00:09:05.678", "label": "N\u00fameros 16:27", "endTransitionDuration": "00:00:01.167"}, {"duration": "00:00:19.519", "verseNumber": 28, "startTime": "00:09:29.502", "label": "N\u00fameros 16:28", "endTransitionDuration": "00:00:00.000"}, {"duration": "00:00:22.322", "verseNumber": 29, "startTime": "00:09:49.021", "label": "N\u00fameros 16:29", "endTransitionDuration": "00:00:00.000"}, {"duration": "00:00:26.559", "verseNumber": 30, "startTime": "00:10:11.344", "label": "N\u00fameros 16:30", "endTransitionDuration": "00:00:00.000"}, {"duration": "00:00:06.439", "verseNumber": 31, "startTime": "00:10:37.903", "label": "N\u00fameros 16:31", "endTransitionDuration": "00:00:00.000"}, {"duration": "00:00:21.588", "verseNumber": 32, "startTime": "00:10:44.343", "label": "N\u00fameros 16:32", "endTransitionDuration": "00:00:00.000"}, {"duration": "00:00:06.039", "verseNumber": 33, "startTime": "00:11:05.931", "label": "N\u00fameros 16:33", "endTransitionDuration": "00:00:00.000"}, {"duration": "00:00:15.315", "verseNumber": 34, "startTime": "00:11:11.971", "label": "N\u00fameros 16:34", "endTransitionDuration": "00:00:00.000"}, {"duration": "00:00:16.916", "verseNumber": 35, "startTime": "00:11:27.286", "label": "N\u00fameros 16:35", "endTransitionDuration": "00:00:01.167"}, {"duration": "00:00:03.103", "verseNumber": 36, "startTime": "00:11:44.203", "label": "N\u00fameros 16:36", "endTransitionDuration": "00:00:00.000"}, {"duration": "00:00:45.845", "verseNumber": 37, "startTime": "00:11:47.306", "label": "N\u00fameros 16:37", "endTransitionDuration": "00:00:00.000"}, {"duration": "00:00:51.418", "verseNumber": 38, "startTime": "00:12:33.152", "label": "N\u00fameros 16:38", "endTransitionDuration": "00:00:00.000"}, {"duration": "00:00:36.970", "verseNumber": 39, "startTime": "00:13:24.570", "label": "N\u00fameros 16:39", "endTransitionDuration": "00:00:00.000"}, {"duration": "00:00:43.109", "verseNumber": 40, "startTime": "00:14:01.540", "label": "N\u00fameros 16:40", "endTransitionDuration": "00:00:01.167"}, {"duration": "00:00:20.653", "verseNumber": 41, "startTime": "00:14:44.650", "label": "N\u00fameros 16:41", "endTransitionDuration": "00:00:00.000"}, {"duration": "00:00:16.549", "verseNumber": 42, "startTime": "00:15:05.304", "label": "N\u00fameros 16:42", "endTransitionDuration": "00:00:00.000"}, {"duration": "00:00:06.606", "verseNumber": 43, "startTime": "00:15:21.854", "label": "N\u00fameros 16:43", "endTransitionDuration": "00:00:00.000"}, {"duration": "00:00:03.036", "verseNumber": 44, "startTime": "00:15:28.460", "label": "N\u00fameros 16:44", "endTransitionDuration": "00:00:00.000"}, {"duration": "00:00:12.145", "verseNumber": 45, "startTime": "00:15:31.497", "label": "N\u00fameros 16:45", "endTransitionDuration": "00:00:00.000"}, {"duration": "00:00:34.934", "verseNumber": 46, "startTime": "00:15:43.642", "label": "N\u00fameros 16:46", "endTransitionDuration": "00:00:00.000"}, {"duration": "00:00:21.588", "verseNumber": 47, "startTime": "00:16:18.577", "label": "N\u00fameros 16:47", "endTransitionDuration": "00:00:00.000"}, {"duration": "00:00:10.710", "verseNumber": 48, "startTime": "00:16:40.165", "label": "N\u00fameros 16:48", "endTransitionDuration": "00:00:00.000"}, {"duration": "00:00:22.756", "verseNumber": 49, "startTime": "00:16:50.876", "label": "N\u00fameros 16:49", "endTransitionDuration": "00:00:00.000"}, {"duration": "00:00:18.218", "verseNumber": 50, "startTime": "00:17:13.632", "label": "N\u00fameros 16:50", "endTransitionDuration": "00:00:07.007"}], "hash": "12345678901234567890123456789012", "introduction": {"duration": "00:00:02.001", "startTime": "00:00:00.000"}, "BookName": "N\u00fameros", "file": "https://download-a.akamaihd.net/files/media_publication/ed/nwt_04_Nu_LSB_16_r720P.mp4"}